nabla/__init__.py
nabla/core/__init__.py
nabla/core/execution_context.py
nabla/core/graph_execution.py
nabla/core/tensor.py
nabla/nn/__init__.py
nabla/nn/architectures/__init__.py
nabla/nn/architectures/mlp.py
nabla/nn/init/__init__.py
nabla/nn/init/variance_scaling.py
nabla/nn/layers/__init__.py
nabla/nn/layers/activations.py
nabla/nn/layers/linear.py
nabla/nn/losses/__init__.py
nabla/nn/losses/classification.py
nabla/nn/losses/regression.py
nabla/nn/optim/__init__.py
nabla/nn/optim/adam.py
nabla/nn/optim/adamw.py
nabla/nn/optim/schedules.py
nabla/nn/optim/sgd.py
nabla/nn/utils/__init__.py
nabla/nn/utils/metrics.py
nabla/nn/utils/regularization.py
nabla/nn/utils/training.py
nabla/ops/__init__.py
nabla/ops/binary.py
nabla/ops/creation.py
nabla/ops/indexing.py
nabla/ops/linalg.py
nabla/ops/operation.py
nabla/ops/reduce.py
nabla/ops/special.py
nabla/ops/unary.py
nabla/ops/view.py
nabla/ops/kernels/__init__.mojo
nabla/transforms/__init__.py
nabla/transforms/grad.py
nabla/transforms/jacfwd.py
nabla/transforms/jacrev.py
nabla/transforms/jit.py
nabla/transforms/jvp.py
nabla/transforms/utils.py
nabla/transforms/vjp.py
nabla/transforms/vmap.py
nabla/utils/__init__.py
nabla/utils/docs.py
nabla/utils/formatting.py
nabla/utils/grad_utils.py
nabla/utils/max_interop.py
nabla/utils/shape_utils.py
nabla/utils/testing.py
nabla/utils/types.py
nabla_ml-25.10191431.dist-info/METADATA
nabla_ml-25.10191431.dist-info/WHEEL
nabla_ml-25.10191431.dist-info/top_level.txt
nabla_ml-25.10191431.dist-info/RECORD
