Metadata-Version: 2.4
Name: nabla_ml
Version: 25.10191431
Summary: Dynamic neural networks and function transformations in Python + Mojo
Author-email: TilliFe <tillmann.fehrenbach@gmail.com>
Project-URL: Homepage, https://github.com/nabla-ml/nabla
Project-URL: Repository, https://github.com/nabla-ml/nabla
Project-URL: Bug Tracker, https://github.com/nabla-ml/nabla/issues
Keywords: deep learning,machine learning,jax,autodiff,nabla,mojo,max,gpu,vmap,grad
Classifier: Development Status :: 3 - Alpha
Classifier: Intended Audience :: Developers
Classifier: Intended Audience :: Science/Research
Classifier: Programming Language :: Python :: 3
Classifier: Programming Language :: Python :: 3.10
Classifier: Programming Language :: Python :: 3.11
Classifier: Programming Language :: Python :: 3.12
Classifier: Operating System :: OS Independent
Classifier: Topic :: Scientific/Engineering :: Artificial Intelligence
Classifier: Topic :: Software Development :: Libraries :: Python Modules
Requires-Python: >=3.10
Requires-Dist: numpy>=2.0.0
Requires-Dist: modular>=25.0.0
Provides-Extra: dev
Requires-Dist: pytest>=7.0; extra == "dev"
Requires-Dist: ruff; extra == "dev"
Requires-Dist: black; extra == "dev"
Requires-Dist: mypy; extra == "dev"
Requires-Dist: build; extra == "dev"
Requires-Dist: twine; extra == "dev"
Requires-Dist: pre-commit; extra == "dev"
